{
  "format": "contactsfreeshare.app_update.v1",
  "latest_version": "1.152",
  "release_date": "2026-05-22",
  "notes": "Fix stale shared contacts upload banner after delete or restore.",
  "packages": {
    "mac": {
      "label": "Mac",
      "filename": "ContactsFreeShare-1.152-mac.zip",
      "download_url": "ContactsFreeShare-1.152-mac.zip",
      "file_id": "",
      "mime_type": "application/zip"
    },
    "windows": {
      "label": "Windows",
      "filename": "ContactsFreeShare-1.152-windows.zip",
      "download_url": "ContactsFreeShare-1.152-windows.zip",
      "file_id": "",
      "mime_type": "application/zip"
    }
  }
}
